pylebedev/__init__.py
pylebedev/_version.py
pylebedev/pylebedev.py
pylebedev/data/lebedev_003.txt
pylebedev/data/lebedev_005.txt
pylebedev/data/lebedev_007.txt
pylebedev/data/lebedev_009.txt
pylebedev/data/lebedev_011.txt
pylebedev/data/lebedev_013.txt
pylebedev/data/lebedev_015.txt
pylebedev/data/lebedev_017.txt
pylebedev/data/lebedev_019.txt
pylebedev/data/lebedev_021.txt
pylebedev/data/lebedev_023.txt
pylebedev/data/lebedev_025.txt
pylebedev/data/lebedev_027.txt
pylebedev/data/lebedev_029.txt
pylebedev/data/lebedev_031.txt
pylebedev/data/lebedev_035.txt
pylebedev/data/lebedev_041.txt
pylebedev/data/lebedev_047.txt
pylebedev/data/lebedev_053.txt
pylebedev/data/lebedev_059.txt
pylebedev/data/lebedev_065.txt
pylebedev/data/lebedev_071.txt
pylebedev/data/lebedev_077.txt
pylebedev/data/lebedev_083.txt
pylebedev/data/lebedev_089.txt
pylebedev/data/lebedev_095.txt
pylebedev/data/lebedev_101.txt
pylebedev/data/lebedev_107.txt
pylebedev/data/lebedev_113.txt
pylebedev/data/lebedev_119.txt
pylebedev/data/lebedev_125.txt
pylebedev/data/lebedev_131.txt
pylebedev-1.0.1.dist-info/LICENSE
pylebedev-1.0.1.dist-info/METADATA
pylebedev-1.0.1.dist-info/WHEEL
pylebedev-1.0.1.dist-info/top_level.txt
pylebedev-1.0.1.dist-info/RECORD
