Metadata-Version: 2.1
Name: pylebedev
Version: 1.0.1
Summary: pylebedev
Home-page: https://github.com/ifilot/pylebedev
Author: Ivo Filot
Author-email: Ivo Filot <i.a.w.filot@tue.nl>
Maintainer-email: Ivo Filot <i.a.w.filot@tue.nl>
License: GPL-3.0-or-later
Project-URL: Homepage, https://github.com/ifilot/pylebedev
Project-URL: Bug Tracker, https://github.com/ifilot/pylebedev/issues
Classifier: Programming Language :: Python :: 3
Classifier: Operating System :: OS Independent
Requires-Python: >=3.6
License-File: LICENSE
Requires-Dist: numpy
